mpio/__init__.py
mpio/adc.py
mpio/devmem.py
mpio/gpio.py
mpio/i2c.py
mpio/input.py
mpio/ioctl.py
mpio/led.py
mpio/pwm.py
mpio/serial.py
mpio/smbus.py
mpio/spi.py
mpio/utils.py
mpio-1.5.dist-info/LICENSE
mpio-1.5.dist-info/LICENSE.MIT
mpio-1.5.dist-info/METADATA
mpio-1.5.dist-info/WHEEL
mpio-1.5.dist-info/top_level.txt
mpio-1.5.dist-info/RECORD
