Metadata-Version: 2.1
Name: mpio
Version: 1.5
Summary: Hardware access for Microchip boards
Author: Joshua Henderson
Author-email: joshua.henderson@microchip.com
Classifier: Development Status :: 5 - Production/Stable
Classifier: Intended Audience :: Developers
Classifier: Intended Audience :: Education
Classifier: Intended Audience :: Information Technology
Classifier: License :: OSI Approved :: Apache Software License
Classifier: Operating System :: POSIX
Classifier: Programming Language :: Python :: 2
Classifier: Programming Language :: Python :: 2.7
Classifier: Programming Language :: Python :: 3
Classifier: Topic :: Software Development :: Embedded Systems
Classifier: Topic :: Software Development :: Libraries :: Python Modules
License-File: LICENSE
License-File: LICENSE.MIT
